curitz/__init__.py
curitz/__main__.py
curitz/cli.py
curitz/culistbox.py
curitz/textpad.py
curitz/timed_cache.py
curitz/version.py
curitz-0.9.22.dist-info/licenses/LICENSE
curitz-0.9.22.dist-info/METADATA
curitz-0.9.22.dist-info/WHEEL
curitz-0.9.22.dist-info/entry_points.txt
curitz-0.9.22.dist-info/top_level.txt
curitz-0.9.22.dist-info/RECORD
