Metadata-Version: 2.4
Name: curitz
Version: 0.9.22
Summary: Python ncurses terminal client to Zino
Author-email: Runar Borge <runar.borge@sikt.no>
Maintainer-email: Uninett Opensource <opensource@uninett.no>
License: 
Platform: any
Classifier: Intended Audience :: Information Technology
Classifier: Intended Audience :: System Administrators
Classifier: Programming Language :: Python :: 3 :: Only
Classifier: Programming Language :: Python :: 3.7
Classifier: Programming Language :: Python :: 3.8
Classifier: Programming Language :: Python :: 3.9
Classifier: Programming Language :: Python :: 3.10
Classifier: Programming Language :: Python :: 3.11
Classifier: Programming Language :: Python :: 3.12
Classifier: Topic :: System :: Monitoring
Requires-Python: >=3.7
License-File: LICENSE
Requires-Dist: zinolib<1.0,>=0.10.1
Requires-Dist: dnspython
Provides-Extra: test
Requires-Dist: tox; extra == "test"
Requires-Dist: mypy; extra == "test"
Requires-Dist: flake8; extra == "test"
Requires-Dist: coverage; extra == "test"
Dynamic: license-file
